{"status": "OK", "results": [{"geometry": {"location_type": "APPROXIMATE", "bounds": {"northeast": {"lat": 36.734452, "lng": -121.5904829}, "southwest": {"lat": 36.6388181, "lng": -121.691914}}, "viewport": {"northeast": {"lat": 36.734452, "lng": -121.5904829}, "southwest": {"lat": 36.6388181, "lng": -121.691914}}, "location": {"lat": 36.6777372, "lng": -121.6555013}}, "address_components": [{"long_name": "Salinas", "types": ["locality", "political"], "short_name": "Salinas"}, {"long_name": "Monterey County", "types": ["administrative_area_level_2", "political"], "short_name": "Monterey County"}, {"long_name": "California", "types": ["administrative_area_level_1", "political"], "short_name": "CA"}, {"long_name": "United States", "types": ["country", "political"], "short_name": "US"}], "place_id": "ChIJL3JhTpb4jYARIYHtuhG7EaU", "formatted_address": "Salinas, CA, USA", "types": ["locality", "political"]}]}