{"status": "OK", "results": [{"geometry": {"location_type": "APPROXIMATE", "bounds": {"northeast": {"lat": 47.3190031, "lng": -122.3482139}, "southwest": {"lat": 47.166528, "lng": -122.562265}}, "viewport": {"northeast": {"lat": 47.3190031, "lng": -122.3482139}, "southwest": {"lat": 47.166528, "lng": -122.562265}}, "location": {"lat": 47.2528768, "lng": -122.4442906}}, "address_components": [{"long_name": "Tacoma", "types": ["locality", "political"], "short_name": "Tacoma"}, {"long_name": "Pierce County", "types": ["administrative_area_level_2", "political"], "short_name": "Pierce County"}, {"long_name": "Washington", "types": ["administrative_area_level_1", "political"], "short_name": "WA"}, {"long_name": "United States", "types": ["country", "political"], "short_name": "US"}], "place_id": "ChIJZ5VlK-5UkFQRgp6w6wecIWI", "formatted_address": "Tacoma, WA, USA", "types": ["locality", "political"]}]}