{"status": "OK", "results": [{"geometry": {"location_type": "APPROXIMATE", "bounds": {"northeast": {"lat": 35.9299121, "lng": -80.04064989999999}, "southwest": {"lat": 35.8310369, "lng": -80.13772689999999}}, "viewport": {"northeast": {"lat": 35.9299121, "lng": -80.04064989999999}, "southwest": {"lat": 35.8310369, "lng": -80.13772689999999}}, "location": {"lat": 35.8826369, "lng": -80.0819879}}, "address_components": [{"long_name": "Thomasville", "types": ["locality", "political"], "short_name": "Thomasville"}, {"long_name": "Thomasville", "types": ["administrative_area_level_3", "political"], "short_name": "Thomasville"}, {"long_name": "Davidson County", "types": ["administrative_area_level_2", "political"], "short_name": "Davidson County"}, {"long_name": "North Carolina", "types": ["administrative_area_level_1", "political"], "short_name": "NC"}, {"long_name": "United States", "types": ["country", "political"], "short_name": "US"}], "place_id": "ChIJP4KqKZkKU4gRZ9aZtwoVeyc", "formatted_address": "Thomasville, NC, USA", "types": ["locality", "political"]}]}