{"status": "OK", "results": [{"geometry": {"location_type": "APPROXIMATE", "bounds": {"northeast": {"lat": 40.248298, "lng": -74.728904}, "southwest": {"lat": 40.1842565, "lng": -74.8193402}}, "viewport": {"northeast": {"lat": 40.248298, "lng": -74.728904}, "southwest": {"lat": 40.1842565, "lng": -74.8193402}}, "location": {"lat": 40.2170534, "lng": -74.7429384}}, "address_components": [{"long_name": "Trenton", "types": ["locality", "political"], "short_name": "Trenton"}, {"long_name": "Mercer County", "types": ["administrative_area_level_2", "political"], "short_name": "Mercer County"}, {"long_name": "New Jersey", "types": ["administrative_area_level_1", "political"], "short_name": "NJ"}, {"long_name": "United States", "types": ["country", "political"], "short_name": "US"}], "place_id": "ChIJubs9LUhDwYkRvNdciX9WFs8", "formatted_address": "Trenton, NJ, USA", "types": ["locality", "political"]}]}