{"status": "OK", "results": [{"geometry": {"location_type": "APPROXIMATE", "bounds": {"northeast": {"lat": 37.537325, "lng": -120.8120129}, "southwest": {"lat": 37.4661451, "lng": -120.9036935}}, "viewport": {"northeast": {"lat": 37.537325, "lng": -120.8120129}, "southwest": {"lat": 37.4661451, "lng": -120.9036935}}, "location": {"lat": 37.4946568, "lng": -120.8465941}}, "address_components": [{"long_name": "Turlock", "types": ["locality", "political"], "short_name": "Turlock"}, {"long_name": "Stanislaus County", "types": ["administrative_area_level_2", "political"], "short_name": "Stanislaus County"}, {"long_name": "California", "types": ["administrative_area_level_1", "political"], "short_name": "CA"}, {"long_name": "United States", "types": ["country", "political"], "short_name": "US"}], "place_id": "ChIJyTIabUwGkYARkOZ2pVznH4E", "formatted_address": "Turlock, CA, USA", "types": ["locality", "political"]}]}