{"status": "OK", "results": [{"geometry": {"location_type": "APPROXIMATE", "bounds": {"northeast": {"lat": 32.817994, "lng": -97.659919}, "southwest": {"lat": 32.7163929, "lng": -97.8424429}}, "viewport": {"northeast": {"lat": 32.817994, "lng": -97.659919}, "southwest": {"lat": 32.7163929, "lng": -97.8424429}}, "location": {"lat": 32.7592955, "lng": -97.7972544}}, "address_components": [{"long_name": "Weatherford", "types": ["locality", "political"], "short_name": "Weatherford"}, {"long_name": "Parker County", "types": ["administrative_area_level_2", "political"], "short_name": "Parker County"}, {"long_name": "Texas", "types": ["administrative_area_level_1", "political"], "short_name": "TX"}, {"long_name": "United States", "types": ["country", "political"], "short_name": "US"}], "place_id": "ChIJqSduZKIGToYRAwUP3gTNJOw", "formatted_address": "Weatherford, TX, USA", "types": ["locality", "political"]}]}