{"status": "OK", "results": [{"geometry": {"location_type": "APPROXIMATE", "bounds": {"northeast": {"lat": 21.332137, "lng": -157.9902128}, "southwest": {"lat": 21.3059491, "lng": -158.029155}}, "viewport": {"northeast": {"lat": 21.332137, "lng": -157.9902128}, "southwest": {"lat": 21.3059491, "lng": -158.029155}}, "location": {"lat": 21.313149, "lng": -158.0089992}}, "address_components": [{"long_name": "Ewa Beach", "types": ["locality", "political"], "short_name": "Ewa Beach"}, {"long_name": "Honolulu County", "types": ["administrative_area_level_2", "political"], "short_name": "Honolulu County"}, {"long_name": "Hawaii", "types": ["administrative_area_level_1", "political"], "short_name": "HI"}, {"long_name": "United States", "types": ["country", "political"], "short_name": "US"}], "place_id": "ChIJAXEgXMVkAHwRMax21iaoWx4", "formatted_address": "Ewa Beach, HI, USA", "types": ["locality", "political"]}]}