{"status": "OK", "results": [{"geometry": {"location_type": "APPROXIMATE", "bounds": {"northeast": {"lat": 41.089934, "lng": -83.5783589}, "southwest": {"lat": 40.9926539, "lng": -83.68940409999999}}, "viewport": {"northeast": {"lat": 41.089934, "lng": -83.5783589}, "southwest": {"lat": 40.9926539, "lng": -83.68940409999999}}, "location": {"lat": 41.04422, "lng": -83.6499321}}, "address_components": [{"long_name": "Findlay", "types": ["locality", "political"], "short_name": "Findlay"}, {"long_name": "Hancock County", "types": ["administrative_area_level_2", "political"], "short_name": "Hancock County"}, {"long_name": "Ohio", "types": ["administrative_area_level_1", "political"], "short_name": "OH"}, {"long_name": "United States", "types": ["country", "political"], "short_name": "US"}, {"long_name": "45840", "types": ["postal_code"], "short_name": "45840"}], "place_id": "ChIJ-XEfmSACPIgR0q4QZwtUtSM", "formatted_address": "Findlay, OH 45840, USA", "types": ["locality", "political"]}, {"geometry": {"location": {"lat": 41.013599, "lng": -83.66860199999999}, "viewport": {"northeast": {"lat": 41.0149479802915, "lng": -83.66725301970848}, "southwest": {"lat": 41.0122500197085, "lng": -83.6699509802915}}, "location_type": "APPROXIMATE"}, "address_components": [{"long_name": "Findlay Airport", "types": ["point_of_interest", "establishment"], "short_name": "Findlay Airport"}, {"long_name": "1615", "types": ["street_number"], "short_name": "1615"}, {"long_name": "Gray Street", "types": ["route"], "short_name": "Gray St"}, {"long_name": "Findlay", "types": ["locality", "political"], "short_name": "Findlay"}, {"long_name": "Hancock County", "types": ["administrative_area_level_2", "political"], "short_name": "Hancock County"}, {"long_name": "Ohio", "types": ["administrative_area_level_1", "political"], "short_name": "OH"}, {"long_name": "United States", "types": ["country", "political"], "short_name": "US"}, {"long_name": "45840", "types": ["postal_code"], "short_name": "45840"}], "place_id": "ChIJzViGqR6sPogRZCnFhRC4HVw", "formatted_address": "Findlay Airport (FDY), 1615 Gray St, Findlay, OH 45840, USA", "types": ["airport", "point_of_interest", "establishment"]}]}