{"status": "OK", "results": [{"geometry": {"location_type": "APPROXIMATE", "bounds": {"northeast": {"lat": 40.98828109999999, "lng": -73.8106841}, "southwest": {"lat": 40.900479, "lng": -73.91124409999999}}, "viewport": {"northeast": {"lat": 40.98828109999999, "lng": -73.8106841}, "southwest": {"lat": 40.900479, "lng": -73.91124409999999}}, "location": {"lat": 40.9312099, "lng": -73.89874689999999}}, "address_components": [{"long_name": "Yonkers", "types": ["locality", "political"], "short_name": "Yonkers"}, {"long_name": "Westchester County", "types": ["administrative_area_level_2", "political"], "short_name": "Westchester County"}, {"long_name": "New York", "types": ["administrative_area_level_1", "political"], "short_name": "NY"}, {"long_name": "United States", "types": ["country", "political"], "short_name": "US"}], "place_id": "ChIJoa9DCQjAwokRotrYpIRzlr4", "formatted_address": "Yonkers, NY, USA", "types": ["locality", "political"]}]}